python_rules_evaluator/__init__.py
python_rules_evaluator/evaluator.py
python_rules_evaluator/input.py
python_rules_evaluator/modules/__init__.py
python_rules_evaluator/modules/functions.py
python_rules_evaluator/modules/jsongeek.py
python_rules_evaluator/modules/profiler.py
python_rules_evaluator-1.4.dist-info/METADATA
python_rules_evaluator-1.4.dist-info/WHEEL
python_rules_evaluator-1.4.dist-info/top_level.txt
python_rules_evaluator-1.4.dist-info/RECORD
