Metadata-Version: 2.1
Name: python-rules-evaluator
Version: 1.4
Summary: Python Rules Evaluator
Home-page: https://github.com/dameyerdave/python-rules-evaluator
Author: David Meyer
Author-email: dameyerdave@gmail.com
License: UNKNOWN
Platform: UNKNOWN
Classifier: Programming Language :: Python :: 3
Classifier: License :: OSI Approved :: MIT License
Classifier: Operating System :: OS Independent
Requires-Python: >=3.5
Requires-Dist: pyyaml
Requires-Dist: friendlylog
